sqlstate
