Metadata-Version: 2.1
Name: sqlstate
Version: 0.0.2
Summary: A lightweight state framework for Python applications
Home-page: https://github.com/marzukia/sqlstate
Author: Andryo Marzuki
Author-email: stabbish@gmail.com
License: UNKNOWN
Platform: UNKNOWN
Classifier: Programming Language :: Python :: 3
Classifier: License :: OSI Approved :: MIT License
Classifier: Operating System :: OS Independent
Requires-Python: >=3.6
